cppython-0.9.10.dist-info/METADATA
cppython-0.9.10.dist-info/WHEEL
cppython-0.9.10.dist-info/entry_points.txt
cppython-0.9.10.dist-info/licenses/LICENSE.md
cppython/__init__.py
cppython/builder.py
cppython/configuration.py
cppython/console/__init__.py
cppython/console/entry.py
cppython/console/schema.py
cppython/core/__init__.py
cppython/core/exception.py
cppython/core/plugin_schema/__init__.py
cppython/core/plugin_schema/generator.py
cppython/core/plugin_schema/provider.py
cppython/core/plugin_schema/scm.py
cppython/core/resolution.py
cppython/core/schema.py
cppython/data.py
cppython/defaults.py
cppython/plugins/__init__.py
cppython/plugins/cmake/__init__.py
cppython/plugins/cmake/builder.py
cppython/plugins/cmake/plugin.py
cppython/plugins/cmake/resolution.py
cppython/plugins/cmake/schema.py
cppython/plugins/conan/__init__.py
cppython/plugins/conan/builder.py
cppython/plugins/conan/plugin.py
cppython/plugins/conan/resolution.py
cppython/plugins/conan/schema.py
cppython/plugins/git/__init__.py
cppython/plugins/git/plugin.py
cppython/plugins/pdm/__init__.py
cppython/plugins/pdm/plugin.py
cppython/plugins/vcpkg/__init__.py
cppython/plugins/vcpkg/plugin.py
cppython/plugins/vcpkg/resolution.py
cppython/plugins/vcpkg/schema.py
cppython/project.py
cppython/py.typed
cppython/schema.py
cppython/test/__init__.py
cppython/test/data/__init__.py
cppython/test/data/mocks.py
cppython/test/mock/__init__.py
cppython/test/mock/generator.py
cppython/test/mock/interface.py
cppython/test/mock/provider.py
cppython/test/mock/scm.py
cppython/test/pytest/__init__.py
cppython/test/pytest/contracts.py
cppython/test/pytest/fixtures.py
cppython/test/pytest/mixins.py
cppython/utility/__init__.py
cppython/utility/exception.py
cppython/utility/filesystem.py
cppython/utility/plugin.py
cppython/utility/py.typed
cppython/utility/utility.py
cppython-0.9.10.dist-info/RECORD
