Metadata-Version: 2.1
Name: cppython
Version: 0.9.10
Summary: A Python management solution for C++ dependencies
Author-Email: Synodic Software <contact@synodic.software>
License: MIT
Project-URL: homepage, https://github.com/Synodic-Software/CPPython
Project-URL: repository, https://github.com/Synodic-Software/CPPython
Requires-Python: >=3.14
Requires-Dist: typer>=0.20.0
Requires-Dist: pydantic>=2.12.4
Requires-Dist: packaging>=25.0
Requires-Dist: requests>=2.32.5
Requires-Dist: types-requests>=2.32.4.20250913
Provides-Extra: pytest
Requires-Dist: pytest>=9.0.1; extra == "pytest"
Requires-Dist: pytest-mock>=3.15.1; extra == "pytest"
Provides-Extra: git
Requires-Dist: dulwich>=0.24.10; extra == "git"
Provides-Extra: pdm
Requires-Dist: pdm>=2.26.1; extra == "pdm"
Provides-Extra: cmake
Requires-Dist: cmake>=4.1.2; extra == "cmake"
Provides-Extra: conan
Requires-Dist: conan>=2.22.2; extra == "conan"
